odoo10_addon_stock_picking_customer_ref-10.0.1.0.0-py2.7-nspkg.pth
odoo/addons/stock_picking_customer_ref/README.rst
odoo/addons/stock_picking_customer_ref/__init__.py
odoo/addons/stock_picking_customer_ref/__manifest__.py
odoo/addons/stock_picking_customer_ref/i18n/es.po
odoo/addons/stock_picking_customer_ref/i18n/pt_BR.po
odoo/addons/stock_picking_customer_ref/i18n/sl.po
odoo/addons/stock_picking_customer_ref/models/__init__.py
odoo/addons/stock_picking_customer_ref/models/stock_picking.py
odoo/addons/stock_picking_customer_ref/tests/__init__.py
odoo/addons/stock_picking_customer_ref/tests/test_stock_picking_customer_ref.py
odoo/addons/stock_picking_customer_ref/views/stock_picking_view.xml
odoo10_addon_stock_picking_customer_ref-10.0.1.0.0.dist-info/DESCRIPTION.rst
odoo10_addon_stock_picking_customer_ref-10.0.1.0.0.dist-info/METADATA
odoo10_addon_stock_picking_customer_ref-10.0.1.0.0.dist-info/RECORD
odoo10_addon_stock_picking_customer_ref-10.0.1.0.0.dist-info/WHEEL
odoo10_addon_stock_picking_customer_ref-10.0.1.0.0.dist-info/metadata.json
odoo10_addon_stock_picking_customer_ref-10.0.1.0.0.dist-info/namespace_packages.txt
odoo10_addon_stock_picking_customer_ref-10.0.1.0.0.dist-info/top_level.txt
